textbuddy/__init__.py
textbuddy/utils.py
textbuddy-0.3.4.dist-info/licenses/LICENSE
textbuddy-0.3.4.dist-info/METADATA
textbuddy-0.3.4.dist-info/WHEEL
textbuddy-0.3.4.dist-info/top_level.txt
textbuddy-0.3.4.dist-info/RECORD
