Metadata-Version: 2.4
Name: textbuddy
Version: 0.3.4
Summary: Simple string and text utilities for Indian contexts for beginners.
Author-email: Amit Dutta <amitdutta4255@gmail.com>
Project-URL: Homepage, https://github.com/notamitgamer/textbuddy
Project-URL: Bug Tracker, https://github.com/notamitgamer/textbuddy/issues
Keywords: india,text,string,currency,phone,date,beginner,utilities
Classifier: Programming Language :: Python :: 3
Classifier: License :: OSI Approved :: MIT License
Classifier: Operating System :: OS Independent
Classifier: Topic :: Text Processing
Classifier: Topic :: Office/Business
Classifier: Intended Audience :: Education
Classifier: Development Status :: 3 - Alpha
Requires-Python: >=3.7
License-File: LICENSE
Dynamic: license-file
